DEERPREdict/DEER.py
DEERPREdict/PRE.py
DEERPREdict/__init__.py
DEERPREdict/lennardjones.py
DEERPREdict/libraries.py
DEERPREdict/utils.py
DEERPREdict/lib/BAS.dcd
DEERPREdict/lib/BAS.pdb
DEERPREdict/lib/BAS_weights.txt
DEERPREdict/lib/MA1.dcd
DEERPREdict/lib/MA1.pdb
DEERPREdict/lib/MA1_weights.txt
DEERPREdict/lib/MTSSL_175K_CaSd_216.dcd
DEERPREdict/lib/MTSSL_175K_CaSd_216.txt
DEERPREdict/lib/MTSSL_175K_CaSd_216_weights.txt
DEERPREdict/lib/MTSSL_175K_X1X2.pdb
DEERPREdict/lib/MTSSL_175K_X1X2_46.dcd
DEERPREdict/lib/MTSSL_175K_X1X2_46.txt
DEERPREdict/lib/MTSSL_175K_X1X2_46_weights.txt
DEERPREdict/lib/MTSSL_CaSd.pdb
DEERPREdict/lib/R1A.dcd
DEERPREdict/lib/R1A.pdb
DEERPREdict/lib/R1A_298K_UFF_216_r1_CASD.dcd
DEERPREdict/lib/R1A_298K_UFF_216_r1_CASD.txt
DEERPREdict/lib/R1A_298K_UFF_216_r1_CASD_weights.txt
DEERPREdict/lib/R1A_298K_UFF_216_r2_CASD.dcd
DEERPREdict/lib/R1A_298K_UFF_216_r2_CASD.txt
DEERPREdict/lib/R1A_298K_UFF_216_r2_CASD_weights.txt
DEERPREdict/lib/R1A_298K_UFF_216_r3_CASD.dcd
DEERPREdict/lib/R1A_298K_UFF_216_r3_CASD.txt
DEERPREdict/lib/R1A_298K_UFF_216_r3_CASD_weights.txt
DEERPREdict/lib/R1A_298K_UFF_216_r4_CASD.dcd
DEERPREdict/lib/R1A_298K_UFF_216_r4_CASD.txt
DEERPREdict/lib/R1A_298K_UFF_216_r4_CASD_weights.txt
DEERPREdict/lib/R1A_298K_UFF_216_r5_CASD.dcd
DEERPREdict/lib/R1A_298K_UFF_216_r5_CASD.txt
DEERPREdict/lib/R1A_298K_UFF_216_r5_CASD_weights.txt
DEERPREdict/lib/R1A_weights.txt
DEERPREdict/lib/gen_rot_lib_MMMx.ipynb
DEERPREdict/lib/libraries.yml
DEERPREdict-0.2.2.dist-info/LICENSE
DEERPREdict-0.2.2.dist-info/METADATA
DEERPREdict-0.2.2.dist-info/WHEEL
DEERPREdict-0.2.2.dist-info/top_level.txt
DEERPREdict-0.2.2.dist-info/RECORD
