Metadata-Version: 2.1
Name: DEERPREdict
Version: 0.2.2
Summary: A package for DEER and PRE predictions based on molecular dynamics ensembles. Can be installed with pip.
Home-page: https://github.com/KULL-Centre/DEERpredict
Author: Giulio Tesei, João M Martins, Micha BA Kunze, Ramon Crehuet, and Kresten Lindorff-Larsen
Author-email: giulio.tesei@bio.ku.dk
License: GPLv3
Classifier: Environment :: Console
Classifier: Development Status :: 3 - Alpha
Classifier: Intended Audience :: Developers
Classifier: Programming Language :: Python
Classifier: Programming Language :: Python :: 3
Classifier: Natural Language :: English
Classifier: Operating System :: OS Independent
Classifier: Topic :: Scientific/Engineering :: Bio-Informatics
Classifier: Topic :: Scientific/Engineering :: Chemistry
Classifier: License :: OSI Approved :: GNU General Public License (GPL)
License-File: LICENSE
Requires-Dist: Cython
Requires-Dist: MDAnalysis
Requires-Dist: numpy
Requires-Dist: pandas
Requires-Dist: matplotlib
Requires-Dist: scipy
Requires-Dist: h5py
Requires-Dist: pyyaml
Requires-Dist: sphinx
Requires-Dist: recommonmark
Requires-Dist: pytest
Requires-Dist: sphinx-rtd-theme
Requires-Dist: sphinx-math-dollar
Requires-Dist: sphinx-markdown-tables
